[
  {
    "レア": 1,
    "名称": "レザーベルト",
    "購入": 200,
    "売却": 50,
    "性能変化_攻": 2,
    "性能変化_防": 0,
    "性能変化_速": 2,
    "性能変化_知": 0,
    "能力付加": [
      "矮小体躯:2"
    ],
    "説明": "革製のベルト。腰をキュっとしめて、少しでもスリムに見せよう。"
  },
  {
    "レア": 1,
    "名称": "調教鞭",
    "購入": 200,
    "売却": 50,
    "性能変化_攻": 3,
    "性能変化_防": 0,
    "性能変化_速": 1,
    "性能変化_知": 0,
    "能力付加": [
      "人間支配:2"
    ],
    "説明": "痛みを与える事に特化した鞭。"
  },
  {
    "レア": 1,
    "名称": "ネコジャラシの鞭",
    "購入": 200,
    "売却": 50,
    "性能変化_攻": 1,
    "性能変化_防": 0,
    "性能変化_速": 3,
    "性能変化_知": 0,
    "能力付加": [
      "奇襲戦法:3",
      "先陣の誉"
    ],
    "説明": "気を逸らして不意打ちする鞭"
  },
  {
    "レア": 1,
    "名称": "砕石袋",
    "購入": 200,
    "売却": 50,
    "性能変化_攻": 5,
    "性能変化_防": -1,
    "性能変化_速": 0,
    "性能変化_知": 0,
    "能力付加": [
      "撃破金運:1"
    ],
    "説明": "砂と石を詰めてずっしりとした袋。"
  },
  {
    "レア": 1,
    "名称": "雑草束",
    "購入": 200,
    "売却": 50,
    "性能変化_攻": 0,
    "性能変化_防": 0,
    "性能変化_速": 4,
    "性能変化_知": 0,
    "能力付加": [
      "リカバリ:2"
    ],
    "説明": "いわゆるただの草。しかし、今こそ雑草魂を見せる時だ！"
  },
  {
    "レア": 2,
    "名称": "ヌンチャク",
    "購入": 400,
    "売却": 100,
    "性能変化_攻": 4,
    "性能変化_防": 0,
    "性能変化_速": 4,
    "性能変化_知": 0,
    "能力付加": [
      "パリング:5"
    ],
    "説明": "扱いの難しい特殊な打撃武器。"
  },
  {
    "レア": 2,
    "名称": "イバラ鞭",
    "購入": 400,
    "売却": 100,
    "性能変化_攻": 5,
    "性能変化_防": 0,
    "性能変化_速": 3,
    "性能変化_知": 0,
    "能力付加": [
      "毒化攻撃:7"
    ],
    "説明": "植物の茨から造られた鞭。"
  },
  {
    "レア": 2,
    "名称": "キャットテイル",
    "購入": 400,
    "売却": 100,
    "性能変化_攻": 2,
    "性能変化_防": 2,
    "性能変化_速": 2,
    "性能変化_知": 2,
    "能力付加": [
      "イベイド:3",
      "思考停止"
    ],
    "説明": "ネコのしっぽ鞭。可愛さのあまり思考が停止する。"
  },
  {
    "レア": 2,
    "名称": "呪いの濡れ雑巾",
    "購入": 400,
    "売却": 100,
    "性能変化_攻": 6,
    "性能変化_防": -4,
    "性能変化_速": 6,
    "性能変化_知": 0,
    "能力付加": [
      "戦術妨害:5",
      "遠隔攻撃"
    ],
    "説明": "絞っても水分が抜けない呪いの雑巾。顔に叩きつけることで精神に打撃。"
  },
  {
    "レア": 2,
    "名称": "くすぐり羽",
    "購入": 400,
    "売却": 100,
    "性能変化_攻": 0,
    "性能変化_防": 0,
    "性能変化_速": 6,
    "性能変化_知": 2,
    "能力付加": [
      "不殺の誓",
      "標的後逸"
    ],
    "説明": "近くにいる者をくすぐるには絶好のアイテム。"
  },
  {
    "レア": 3,
    "名称": "鎖鎌",
    "購入": 800,
    "売却": 200,
    "性能変化_攻": 8,
    "性能変化_防": 0,
    "性能変化_速": 4,
    "性能変化_知": 0,
    "能力付加": [
      "側面攻撃:3",
      "樹霊特攻:1"
    ],
    "説明": "鎖と鎌の二つを組み合わせた武器。"
  },
  {
    "レア": 3,
    "名称": "スパイクベルト",
    "購入": 800,
    "売却": 200,
    "性能変化_攻": 10,
    "性能変化_防": 4,
    "性能変化_速": -2,
    "性能変化_知": 0,
    "能力付加": [
      "全力攻撃:10",
      "防御削減:7"
    ],
    "説明": "鉄で装飾された革ベルト鞭。"
  },
  {
    "レア": 3,
    "名称": "若草の鞭",
    "購入": 800,
    "売却": 200,
    "性能変化_攻": 0,
    "性能変化_防": 4,
    "性能変化_速": 4,
    "性能変化_知": 4,
    "能力付加": [
      "自己治癒:5",
      "対術結界:5"
    ],
    "説明": "生命力溢れた若草を束ねて造った鞭。"
  },
  {
    "レア": 3,
    "名称": "バトルヨーヨー",
    "購入": 800,
    "売却": 200,
    "性能変化_攻": 8,
    "性能変化_防": 0,
    "性能変化_速": 4,
    "性能変化_知": 0,
    "能力付加": [
      "遠隔攻撃",
      "カブト割:10"
    ],
    "説明": "流行に敏感な魔界の子供たちの間で人気の、喧嘩ヨーヨー。"
  },
  {
    "レア": 3,
    "名称": "悪魔のしっぽ",
    "購入": 800,
    "売却": 200,
    "性能変化_攻": 8,
    "性能変化_防": 0,
    "性能変化_速": 2,
    "性能変化_知": 2,
    "能力付加": [
      "人間特攻:1",
      "結界の歪:5"
    ],
    "説明": "悪魔族から切り取ってきたと思われるしっぽ。少しピクピクしている。"
  },
  {
    "レア": 4,
    "名称": "フレイル",
    "購入": 1600,
    "売却": 400,
    "性能変化_攻": 10,
    "性能変化_防": 6,
    "性能変化_速": 0,
    "性能変化_知": 0,
    "能力付加": [
      "防御布陣:10",
      "パリング:10"
    ],
    "説明": "長い柄と鎖、打撃部で構成された棍。"
  },
  {
    "レア": 4,
    "名称": "成仏の数珠",
    "購入": 1600,
    "売却": 400,
    "性能変化_攻": 8,
    "性能変化_防": 8,
    "性能変化_速": -4,
    "性能変化_知": 4,
    "能力付加": [
      "死者特攻:1",
      "死者支配:6"
    ],
    "説明": "コレを持てば、物理的に敵を成仏させることが出来る。"
  },
  {
    "レア": 4,
    "名称": "アイドルリボン",
    "購入": 1600,
    "売却": 400,
    "性能変化_攻": 0,
    "性能変化_防": 0,
    "性能変化_速": 8,
    "性能変化_知": 8,
    "能力付加": [
      "師団活性:5",
      "トレハン:4"
    ],
    "説明": "つけるだけでアイドル気分に浸れる不思議なリボン。"
  },
  {
    "レア": 4,
    "名称": "デッドリーケンダマ",
    "購入": 1600,
    "売却": 400,
    "性能変化_攻": 10,
    "性能変化_防": 0,
    "性能変化_速": 6,
    "性能変化_知": 0,
    "能力付加": [
      "必殺増加:10",
      "奇襲戦法:10"
    ],
    "説明": "油断すると当たり所が悪くて死ぬ危険なトゲ付きけん玉。"
  },
  {
    "レア": 4,
    "名称": "火焔鳥の羽",
    "購入": 1600,
    "売却": 400,
    "性能変化_攻": 12,
    "性能変化_防": 0,
    "性能変化_速": 0,
    "性能変化_知": 4,
    "能力付加": [
      "リカバリ:15",
      "イベイド:10"
    ],
    "説明": "火を纏った怪鳥の羽根。振ると火の粉をまき散らす。"
  },
  {
    "レア": 5,
    "名称": "電撃鉄球",
    "購入": 3200,
    "売却": 800,
    "性能変化_攻": 16,
    "性能変化_防": 0,
    "性能変化_速": 0,
    "性能変化_知": 4,
    "能力付加": [
      "城壁崩し:60",
      "電撃砲弾:3"
    ],
    "説明": "電撃を纏ったトゲ鉄球。あたり前だが、当たると痛い。"
  },
  {
    "レア": 5,
    "名称": "愛の鞭",
    "購入": 3200,
    "売却": 800,
    "性能変化_攻": 8,
    "性能変化_防": 0,
    "性能変化_速": 6,
    "性能変化_知": 6,
    "能力付加": [
      "反撃倍加:2",
      "特攻防御:30"
    ],
    "説明": "これもまた一つの愛の形。"
  },
  {
    "レア": 5,
    "名称": "触腕",
    "購入": 3200,
    "売却": 800,
    "性能変化_攻": 9,
    "性能変化_防": 2,
    "性能変化_速": 9,
    "性能変化_知": 0,
    "能力付加": [
      "男性活性:8",
      "女性特攻:1"
    ],
    "説明": "名もなき触手の生きた証。"
  },
  {
    "レア": 5,
    "名称": "多節棍",
    "購入": 3200,
    "売却": 800,
    "性能変化_攻": 12,
    "性能変化_防": -4,
    "性能変化_速": 12,
    "性能変化_知": 0,
    "能力付加": [
      "多段攻撃:1",
      "堅守体躯:10"
    ],
    "説明": "無数に折れ曲がることが特徴の棍棒の一種。"
  },
  {
    "レア": 5,
    "名称": "ブレイズウィップ",
    "購入": 3200,
    "売却": 800,
    "性能変化_攻": 14,
    "性能変化_防": 0,
    "性能変化_速": 6,
    "性能変化_知": 0,
    "能力付加": [
      "致命必殺:40",
      "自爆結界:20"
    ],
    "説明": "燃え盛る炎の鞭。"
  },
  {
    "レア": 6,
    "名称": "妖精のしっぽ",
    "購入": 9600,
    "売却": 2400,
    "性能変化_攻": 8,
    "性能変化_防": 0,
    "性能変化_速": 8,
    "性能変化_知": 8,
    "能力付加": [
      "側面攻撃:8",
      "巨人狩り:10"
    ],
    "説明": "妖精が扱う不思議な鞭。何度も叩かれたくなる。ヤミツキアイテム。"
  },
  {
    "レア": 6,
    "名称": "女王様の鞭",
    "購入": 9600,
    "売却": 2400,
    "性能変化_攻": 14,
    "性能変化_防": -4,
    "性能変化_速": 10,
    "性能変化_知": 4,
    "能力付加": [
      "男性特攻:1",
      "必殺増加:25"
    ],
    "説明": "どんな男も一打で屈する魅惑の鞭。"
  },
  {
    "レア": 6,
    "名称": "コメットスター",
    "購入": 9600,
    "売却": 2400,
    "性能変化_攻": 20,
    "性能変化_防": 8,
    "性能変化_速": -4,
    "性能変化_知": 0,
    "能力付加": [
      "カブト割:15",
      "反撃耐性:25"
    ],
    "説明": "やたらと柄がしなる強力な鉄球兵器。この鈍器で思う様殴るべし。"
  },
  {
    "レア": 6,
    "名称": "クラーケンのゲソ",
    "購入": 9600,
    "売却": 2400,
    "性能変化_攻": 8,
    "性能変化_防": 0,
    "性能変化_速": 16,
    "性能変化_知": 0,
    "能力付加": [
      "確率追撃:40",
      "グルメ魂:5"
    ],
    "説明": "イキのいい魔界イカの触手。いざというときの食料としても有用。"
  },
  {
    "レア": 6,
    "名称": "妖精蝶の羽",
    "購入": 9600,
    "売却": 2400,
    "性能変化_攻": 12,
    "性能変化_防": 0,
    "性能変化_速": 6,
    "性能変化_知": 6,
    "能力付加": [
      "矮小体躯:10",
      "イベイド:20"
    ],
    "説明": "妖精蝶の魔力が籠った羽。"
  },
  {
    "レア": 7,
    "名称": "チャンピオンの証",
    "購入": 19200,
    "売却": 4800,
    "性能変化_攻": 10,
    "性能変化_防": 10,
    "性能変化_速": 8,
    "性能変化_知": 0,
    "能力付加": [
      "扇形攻撃",
      "必殺増加:15"
    ],
    "説明": "コレでアナタもチャンピオン。王者のベルトでひっぱたけば強い筈。"
  },
  {
    "レア": 7,
    "名称": "雷公鞭",
    "購入": 19200,
    "売却": 4800,
    "性能変化_攻": 12,
    "性能変化_防": 0,
    "性能変化_速": 6,
    "性能変化_知": 10,
    "能力付加": [
      "乾坤一擲:25",
      "大雷撃陣:7"
    ],
    "説明": "伝説にのみ存在するとされる幻の鞭。"
  },
  {
    "レア": 7,
    "名称": "マスターヌンチャク",
    "購入": 19200,
    "売却": 4800,
    "性能変化_攻": 14,
    "性能変化_防": 0,
    "性能変化_速": 14,
    "性能変化_知": 0,
    "能力付加": [
      "パリング:20",
      "連携攻撃:35"
    ],
    "説明": "功夫マスターの用いるヌンチャク"
  },
  {
    "レア": 7,
    "名称": "エンジェルチェーン",
    "購入": 19200,
    "売却": 4800,
    "性能変化_攻": 0,
    "性能変化_防": 8,
    "性能変化_速": 12,
    "性能変化_知": 8,
    "能力付加": [
      "封印攻撃",
      "対術結界:25"
    ],
    "説明": "天使が罪人を捕らえるための鎖。どこか愛らしい。"
  },
  {
    "レア": 7,
    "名称": "テイマーズウィップ",
    "購入": 19200,
    "売却": 4800,
    "性能変化_攻": 20,
    "性能変化_防": 0,
    "性能変化_速": 4,
    "性能変化_知": 4,
    "能力付加": [
      "連携攻撃:35",
      "麻痺攻撃:2"
    ],
    "説明": "獣や竜を使役するテイマーの為の鞭。"
  },
  {
    "レア": 8,
    "名称": "ドラゴンテイル",
    "購入": 32000,
    "売却": 8000,
    "性能変化_攻": 32,
    "性能変化_防": 0,
    "性能変化_速": 0,
    "性能変化_知": 0,
    "能力付加": [
      "竜の吐息:5",
      "竜歌共鳴:12"
    ],
    "説明": "竜の尾で造られた、恐ろしき鞭。"
  },
  {
    "レア": 8,
    "名称": "レルネイ",
    "購入": 32000,
    "売却": 8000,
    "性能変化_攻": 10,
    "性能変化_防": 6,
    "性能変化_速": 16,
    "性能変化_知": 0,
    "能力付加": [
      "多段攻撃:2",
      "師団活性:12"
    ],
    "説明": "闇の踊り娘が持つ可変蛇腹剣。"
  },
  {
    "レア": 8,
    "名称": "触主の触腕",
    "購入": 32000,
    "売却": 8000,
    "性能変化_攻": 16,
    "性能変化_防": 0,
    "性能変化_速": 16,
    "性能変化_知": 0,
    "能力付加": [
      "女性特攻:1",
      "確率追撃:88"
    ],
    "説明": "触手は、生き様を背中で語る。それが真のダンディズム。"
  },
  {
    "レア": 8,
    "名称": "コローニアの触槌",
    "購入": 32000,
    "売却": 8000,
    "性能変化_攻": 20,
    "性能変化_防": 12,
    "性能変化_速": 0,
    "性能変化_知": 0,
    "能力付加": [
      "カブト割:25",
      "無形体躯:20"
    ],
    "説明": "スライムメイド少女の可変触腕が槌状になったもの。"
  },
  {
    "レア": 8,
    "名称": "キマイラの毒尾",
    "購入": 32000,
    "売却": 8000,
    "性能変化_攻": 24,
    "性能変化_防": 0,
    "性能変化_速": 8,
    "性能変化_知": 0,
    "能力付加": [
      "巨人狩り:25",
      "毒化攻撃:20"
    ],
    "説明": "魔界のキマイラから切り出され、錬金術で鞭の加工された毒尾。"
  },
  {
    "レア": 9,
    "名称": "ローズウィップ",
    "購入": 64000,
    "売却": null,
    "性能変化_攻": 10,
    "性能変化_防": 20,
    "性能変化_速": 20,
    "性能変化_知": -10,
    "能力付加": [
      "多段攻撃:2",
      "側面攻撃:15"
    ],
    "説明": "アルラウネの女王ヨーキが持つ鞭。"
  },
  {
    "レア": 9,
    "名称": "ナインテールLB",
    "購入": 64000,
    "売却": null,
    "性能変化_攻": 24,
    "性能変化_防": 16,
    "性能変化_速": 0,
    "性能変化_知": 0,
    "能力付加": [
      "女性弱体:20",
      "女性特攻:2"
    ],
    "説明": "九本の尾を持つ可変レーザーウィップ。"
  },
  {
    "レア": 9,
    "名称": "ヘルズヘイム",
    "購入": 64000,
    "売却": null,
    "性能変化_攻": 30,
    "性能変化_防": 0,
    "性能変化_速": 10,
    "性能変化_知": 0,
    "能力付加": [
      "狂奔の牙:15",
      "凍傷気流:10"
    ],
    "説明": "変幻自在の氷結鞭の刃。"
  },
  {
    "レア": 9,
    "名称": "デュアルウィップ",
    "購入": 64000,
    "売却": null,
    "性能変化_攻": 20,
    "性能変化_防": 0,
    "性能変化_速": 20,
    "性能変化_知": 0,
    "能力付加": [
      "確率追撃:100",
      "魔術砲弾:9"
    ],
    "説明": "2段構えな二又の鞭。どこかの二尾の黒猫の尻尾がモチーフ。"
  },
  {
    "レア": 9,
    "名称": "ブレイズスター",
    "購入": 64000,
    "売却": null,
    "性能変化_攻": 32,
    "性能変化_防": 8,
    "性能変化_速": 0,
    "性能変化_知": 0,
    "能力付加": [
      "反撃倍加:3",
      "自決自爆:60"
    ],
    "説明": "燃え盛る魔力の込められたモーニングスター。"
  },
  {
    "レア": 10,
    "名称": "花女王の触腕",
    "購入": 96000,
    "売却": null,
    "性能変化_攻": 0,
    "性能変化_防": 48,
    "性能変化_速": 0,
    "性能変化_知": 0,
    "能力付加": [
      "リカバリ:40",
      "堅守体躯:25"
    ],
    "説明": "アルラウネの女王から無限に採取できるクロロフィルな蔦。"
  },
  {
    "レア": 10,
    "名称": "スヴァティ",
    "購入": 96000,
    "売却": null,
    "性能変化_攻": 24,
    "性能変化_防": 0,
    "性能変化_速": 16,
    "性能変化_知": 8,
    "能力付加": [
      "大氷撃陣:12",
      "全域攻撃"
    ],
    "説明": "冷華の淫狼が持つ高位の魔装。"
  },
  {
    "レア": 10,
    "名称": "触手王の触腕",
    "購入": 96000,
    "売却": null,
    "性能変化_攻": 32,
    "性能変化_防": 0,
    "性能変化_速": 16,
    "性能変化_知": 0,
    "能力付加": [
      "女性特攻:2",
      "全力攻撃:50"
    ],
    "説明": "触手の王が持つ華麗なる触腕。"
  },
  {
    "レア": 10,
    "名称": "リンリアーム",
    "購入": 96000,
    "売却": null,
    "性能変化_攻": 24,
    "性能変化_防": 24,
    "性能変化_速": 0,
    "性能変化_知": 0,
    "能力付加": [
      "多段攻撃:3",
      "無形体躯:25"
    ],
    "説明": "スライム兵長の変幻自在な武装アーム。"
  },
  {
    "レア": 10,
    "名称": "融合式竜尾",
    "購入": 96000,
    "売却": null,
    "性能変化_攻": 32,
    "性能変化_防": 16,
    "性能変化_速": 8,
    "性能変化_知": -8,
    "能力付加": [
      "カブト割:35",
      "パリング:50"
    ],
    "説明": "機械と竜と人を融合した恐るべき実験兵器の竜尾。"
  },
  {
    "レア": 11,
    "名称": "グレイプニール",
    "購入": 128000,
    "売却": null,
    "性能変化_攻": 24,
    "性能変化_防": 0,
    "性能変化_速": 24,
    "性能変化_知": 12,
    "能力付加": [
      "魅了攻撃:2",
      "軍団活性:10"
    ],
    "説明": "欲望の女神が持つという愛情の鎖。"
  },
  {
    "レア": 11,
    "名称": "影皇帝のむち",
    "購入": 128000,
    "売却": null,
    "性能変化_攻": 12,
    "性能変化_防": 0,
    "性能変化_速": 40,
    "性能変化_知": 8,
    "能力付加": [
      "撃破金運:8",
      "トレハン:16"
    ],
    "説明": "世界を闇に染めんと暗躍する組織の幹部クラスに記念贈呈される鞭。"
  },
  {
    "レア": 11,
    "名称": "触手姫の触腕",
    "購入": 128000,
    "売却": null,
    "性能変化_攻": 32,
    "性能変化_防": 12,
    "性能変化_速": 12,
    "性能変化_知": 4,
    "能力付加": [
      "男性特攻:2",
      "カブト割:40"
    ],
    "説明": "触手道を極めるのに性別など関係無い。"
  },
  {
    "レア": 11,
    "名称": "影の凶刃",
    "購入": 128000,
    "売却": null,
    "性能変化_攻": 30,
    "性能変化_防": 20,
    "性能変化_速": 10,
    "性能変化_知": 0,
    "能力付加": [
      "心核穿ち:60",
      "特攻防御:60"
    ],
    "説明": "灰魔姫のブレード付き触手。"
  },
  {
    "レア": 11,
    "名称": "雷鎖剛球",
    "購入": 128000,
    "売却": null,
    "性能変化_攻": 60,
    "性能変化_防": 0,
    "性能変化_速": 0,
    "性能変化_知": 0,
    "能力付加": [
      "必殺増加:25",
      "巨人狩り:50"
    ],
    "説明": "稲妻を放つ剛椀の竜人が愛用した重量のある機巧鉄球。"
  },
  {
    "レア": 12,
    "名称": "ウロボロスの鞭",
    "購入": 192000,
    "売却": null,
    "性能変化_攻": 14,
    "性能変化_防": 50,
    "性能変化_速": 0,
    "性能変化_知": 8,
    "能力付加": [
      "回帰治癒:20",
      "堅守体躯:40"
    ],
    "説明": "無限の双子竜の力を秘めた鞭。"
  },
  {
    "レア": 12,
    "名称": "神荊リンドヴルム",
    "購入": 192000,
    "売却": null,
    "性能変化_攻": 40,
    "性能変化_防": 0,
    "性能変化_速": 32,
    "性能変化_知": 0,
    "能力付加": [
      "確率追撃:100",
      "カブト割:40"
    ],
    "説明": "神竜の尾から作られた輝く棘鞭。"
  },
  {
    "レア": 12,
    "名称": "フォトンスレッド",
    "購入": 192000,
    "売却": null,
    "性能変化_攻": 48,
    "性能変化_防": 24,
    "性能変化_速": 0,
    "性能変化_知": 0,
    "能力付加": [
      "次元斬撃:25",
      "確率追撃:100"
    ],
    "説明": "全てを滅する光炎の鞭。"
  },
  {
    "レア": 12,
    "名称": "月神の蛇血",
    "購入": 192000,
    "売却": null,
    "性能変化_攻": 48,
    "性能変化_防": 12,
    "性能変化_速": 0,
    "性能変化_知": 12,
    "能力付加": [
      "多段攻撃:4",
      "反撃耐性:50"
    ],
    "説明": "闇の女神の血で生まれた可変獣。"
  },
  {
    "レア": 12,
    "名称": "鞭角ミストルテイル",
    "購入": 192000,
    "売却": null,
    "性能変化_攻": 42,
    "性能変化_防": 0,
    "性能変化_速": 24,
    "性能変化_知": 6,
    "能力付加": [
      "連携攻撃:100",
      "側面攻撃:40"
    ],
    "説明": "優秀なヴァルキリーに与えられる天界の神器。自在に可変する聖なる鞭剣。"
  },
  {
    "レア": 13,
    "名称": "禁獣神鞭",
    "購入": 256000,
    "売却": null,
    "性能変化_攻": 84,
    "性能変化_防": 0,
    "性能変化_速": 0,
    "性能変化_知": 0,
    "能力付加": [
      "心核穿ち:75",
      "狂奔の牙:20"
    ],
    "説明": "禁獣の祖となる獣神の毛で作られた剛鞭。"
  },
  {
    "レア": 13,
    "名称": "触神の御手",
    "購入": 256000,
    "売却": null,
    "性能変化_攻": 64,
    "性能変化_防": 0,
    "性能変化_速": 0,
    "性能変化_知": 20,
    "能力付加": [
      "全種特攻:1",
      "致命必殺:50"
    ],
    "説明": "偉大なる触神の触腕。全ての触手がそれを渇望するという。"
  },
  {
    "レア": 13,
    "名称": "深淵の姫の触腕",
    "購入": 256000,
    "売却": null,
    "性能変化_攻": 48,
    "性能変化_防": 14,
    "性能変化_速": 14,
    "性能変化_知": 8,
    "能力付加": [
      "対術結界:50",
      "無形体躯:40"
    ],
    "説明": "深淵に住まうアトラクナクアの触腕。闇に彩られた触手もまた美しい。"
  },
  {
    "レア": 13,
    "名称": "始原獣の触腕",
    "購入": 256000,
    "売却": null,
    "性能変化_攻": 70,
    "性能変化_防": 30,
    "性能変化_速": 0,
    "性能変化_知": -16,
    "能力付加": [
      "巨人狩り:50",
      "確率追撃:150"
    ],
    "説明": "始原の獣が持つという神話的触腕。"
  },
  {
    "レア": 13,
    "名称": "竜牙剣ファングテイル",
    "購入": 256000,
    "売却": null,
    "性能変化_攻": 72,
    "性能変化_防": 0,
    "性能変化_速": 12,
    "性能変化_知": 0,
    "能力付加": [
      "疾風迅雷:25",
      "カブト割:50"
    ],
    "説明": "黙示の魔戦姫が愛用する、邪竜の力を帯びた鞭剣。"
  },
  {
    "レア": 14,
    "名称": "暗獄鞭",
    "購入": 320000,
    "売却": null,
    "性能変化_攻": 120,
    "性能変化_防": -20,
    "性能変化_速": 0,
    "性能変化_知": 0,
    "能力付加": [
      "軍団攻撃:2",
      "無効喰い:35"
    ],
    "説明": "暗獄のマナから生み出される鞭。触れた者を闇で浸食する。"
  },
  {
    "レア": 14,
    "名称": "エリキシルの光鎖",
    "購入": 320000,
    "売却": null,
    "性能変化_攻": 70,
    "性能変化_防": 0,
    "性能変化_速": 20,
    "性能変化_知": 10,
    "能力付加": [
      "次元斬撃:50",
      "多段攻撃:5"
    ],
    "説明": "魔導大公が提唱する新次元のエネルギーを用いた光学兵器の鞭。"
  },
  {
    "レア": 14,
    "名称": "開闢の触腕",
    "購入": 320000,
    "売却": null,
    "性能変化_攻": 25,
    "性能変化_防": 25,
    "性能変化_速": 25,
    "性能変化_知": 25,
    "能力付加": [
      "確率追撃:494",
      "無貌の血"
    ],
    "説明": "大触手時代の幕開けとなる、天地開闢の触手。"
  },
  {
    "レア": 14,
    "名称": "冥神の竜血",
    "購入": 320000,
    "売却": null,
    "性能変化_攻": 100,
    "性能変化_防": 20,
    "性能変化_速": -40,
    "性能変化_知": 20,
    "能力付加": [
      "暴走攻撃:100",
      "特攻防御:100"
    ],
    "説明": "冥界の神が生み出した死をもたらす触腕。"
  },
  {
    "レア": 14,
    "名称": "オブリビオン・エッジ",
    "購入": 320000,
    "売却": null,
    "性能変化_攻": 130,
    "性能変化_防": 0,
    "性能変化_速": 0,
    "性能変化_知": -30,
    "能力付加": [
      "カブト割:75",
      "確率追撃:150"
    ],
    "説明": "塵灰に全ての血を捧げた者が生み出した、狂気の刃。"
  }
]